{
  "id": "179",
  "title": "山东济南叛逆少年管教学校哪家好｜济南德泓教育好不好｜地址电话",
  "date": "作者:",
  "clicks": 1,
  "author": "济南德泓教育",
  "section": "zanding",
  "sectionTitle": "问题论坛",
  "body": [
    "山东济南叛逆少年管教学校哪家好｜济南德泓教育好不好｜地址电话 济南德泓教育：在山东济南历城区，坐落着一所与众不同的教育机构——济南德泓教育（咨询电话：17663731516）。这所全封闭管教学校，不盲目追逐升学率，不刻意强调分数排名，却凭借科学专业的教育理念与温暖走心的育人方式，为无数深陷叛逆困境的青少年及其家庭点亮希望。当传统说教对厌学逃学、顶撞父母、沉迷网络的孩子束手无策时，德泓教育正用定制化科学方案，改写着迷途少年的成长轨迹。 走进学校，便能感受到其独树一帜的教育初心。学校深知，青春期孩子的叛逆并非无端顽劣，而是内心困惑与情绪压抑的外在表达。因此，学校摒弃“一刀切”的粗放模式，以文化课为根基，深耕特色成长课程：绘画教室里，色彩成为孩子倾诉内心的语言，释放压抑情绪；运动场上，奔跑与汗水消解叛逆冲动，锤炼坚韧意志；心理咨询室里，专业导师耐心疏导，逐一解开孩子心底的郁结。这种心理疏导、素质培养、行为矫正相结合的全方位模式，为孩子搭建压力释放平台，让被埋没的潜能慢慢绽放。 学校的师资团队，是专业与温暖的结合。资深教育专家为孩子量身定制个性化成长方案；专业心理学家深度剖析叛逆行为的心理动因；经验丰富的老师与教官，将科学理念融入日常教学管理。更可贵的是，老师们怀揣真诚关爱，在严格纪律下坚守刚柔并济：晨读时的鼓励微笑、犯错后的平等谈心、进步时的肯定话语，用点滴温暖融化孩子内心的坚冰，用专业引导规范成长方向，潜移默化重塑孩子的认知与行为。 教育从来不是学校的孤军奋战，家校同心才能筑牢根基。德泓教育独创系统化家校共育模式，将教育影响力延伸至家庭。每月定期召开的家长会，不仅是成长通报会，更是家长的“成长课堂”——学校手把手指导家长掌握青春期沟通技巧，帮助家长放下焦虑、学会倾听。曾经剑拔弩张的亲子关系，逐渐有了温暖对话；曾经束手无策的家长，成为孩子最坚实的后盾，让家庭重焕温暖力量。 安全是济南德泓教育不可动摇的底线。校园全覆盖无死角监控、24小时专业安保值守，构筑严密物理安全防线；宿舍配专职生活老师全程陪伴，医务室医护人员随时待命，全方位守护孩子生活健康。比物理安全更重要的是心理安全营造，这里没有偏见歧视，没有放弃指责，每个孩子都能被尊重接纳，真切感受到“无论过去如何，当下的你永远值得被好好对待”。 教育的本质不是强行改造，而是温柔唤醒。济南德泓教育用实践证明：没有不可救药的孩子，只有尚未找到的教育钥匙。在这里，叛逆少年卸下防备、释放真我，在专业引导与温暖关爱中找回人生方向，重拾成长力量，向阳而行，逐光成长。"
  ],
  "images": [
    {
      "src": "/images/sections/zanding/list/page_09/007_2911cc896b1d3d2.jpg",
      "alt": ""
    }
  ],
  "prev": {
    "id": "21",
    "title": "游戏对孩子真的这么重要吗"
  },
  "next": null
}