{
  "title": "心理咨询",
  "url": "https://www.jndhjyzx.com/zixun/",
  "modules": [
    {
      "name": "心理咨询",
      "local_dir": "images/心理咨询",
      "images": [
        {
          "original_url": "http://www.jndhjyzx.com/uploadfile/202212/96e14f88ddf0738.png",
          "filename": "001_96e14f88ddf0738.png",
          "alt": "",
          "size_bytes": 30024,
          "downloaded": true
        },
        {
          "original_url": "https://www.jndhjyzx.com/static/a/web/img/nyban.jpg",
          "filename": "002_nyban.jpg",
          "alt": "",
          "size_bytes": 101330,
          "downloaded": true
        },
        {
          "original_url": "http://www.jndhjyzx.com/uploadfile/202212/64d7f87d0df3c77.jpg",
          "filename": "003_64d7f87d0df3c77.jpg",
          "alt": "心理辅导的重要性",
          "size_bytes": 369876,
          "downloaded": true
        },
        {
          "original_url": "https://www.jndhjyzx.com/uploadfile/210425/1-210425225353T0.jpg",
          "filename": "004_1-210425225353T0.jpg",
          "alt": "家长请重视为什么孩子会叛逆、厌学等心理问题",
          "size_bytes": 70895,
          "downloaded": true
        },
        {
          "original_url": "https://www.jndhjyzx.com/uploadfile/210415/1-2104151FU5G9.jpg",
          "filename": "005_1-2104151FU5G9.jpg",
          "alt": "济南德泓教育心理专家指出:教育厌学、叛逆的孩",
          "size_bytes": 95331,
          "downloaded": true
        },
        {
          "original_url": "https://www.jndhjyzx.com/uploadfile/210218/1-21021Q54149414.jpg",
          "filename": "006_1-21021Q54149414.jpg",
          "alt": "家长你懂那么多家庭教育道理，孩子依然叛逆、",
          "size_bytes": 66246,
          "downloaded": true
        },
        {
          "original_url": "https://www.jndhjyzx.com/uploadfile/210401/1-210401221P1519.jpg",
          "filename": "007_1-210401221P1519.jpg",
          "alt": "济南德泓教育心理老师与您分享：创伤导致的心",
          "size_bytes": 77808,
          "downloaded": true
        },
        {
          "original_url": "https://www.jndhjyzx.com/uploadfile/210220/1-2102201513405N.jpg",
          "filename": "008_1-2102201513405N.jpg",
          "alt": "孩子厌学，家长应该怎么处理？",
          "size_bytes": 44624,
          "downloaded": true
        },
        {
          "original_url": "https://www.jndhjyzx.com/uploadfile/201004/1-2010040ZF9394.jpg",
          "filename": "009_1-2010040ZF9394.jpg",
          "alt": "父母经常打骂孩子，导致孩子自卑,厌学！",
          "size_bytes": 30345,
          "downloaded": true
        },
        {
          "original_url": "https://www.jndhjyzx.com/uploadfile/200921/1-200921232T4Q4.jpg",
          "filename": "010_1-200921232T4Q4.jpg",
          "alt": "济南德泓教育心理专家与您分享，青春期孩子早",
          "size_bytes": 66031,
          "downloaded": true
        },
        {
          "original_url": "https://www.jndhjyzx.com/uploadfile/200921/1-200921191J2548.jpg",
          "filename": "011_1-200921191J2548.jpg",
          "alt": "团体心理大课",
          "size_bytes": 80930,
          "downloaded": true
        },
        {
          "original_url": "https://www.jndhjyzx.com/uploadfile/200921/1-20092110523AX.jpg",
          "filename": "012_1-20092110523AX.jpg",
          "alt": "家长学会放手，把独立还给孩子!",
          "size_bytes": 30873,
          "downloaded": true
        },
        {
          "original_url": "https://www.jndhjyzx.com/uploadfile/200918/1-20091R2261RO.jpg",
          "filename": "013_1-20091R2261RO.jpg",
          "alt": "为什么家长要选择正规的教育咨询机构?",
          "size_bytes": 58106,
          "downloaded": true
        },
        {
          "original_url": "https://www.jndhjyzx.com/uploadfile/200908/1-200ZPZ3193M.jpg",
          "filename": "014_1-200ZPZ3193M.jpg",
          "alt": "家长过度的爱会让孩子失去爱他人的能力",
          "size_bytes": 27235,
          "downloaded": true
        },
        {
          "original_url": "http://www.jndhjyzx.com/uploadfile/202212/90229136d5d440.png",
          "filename": "015_90229136d5d440.png",
          "alt": "",
          "size_bytes": 54457,
          "downloaded": true
        }
      ]
    }
  ]
}